gpt4_command_executor/__init__.py
gpt4_command_executor/config.py
gpt4_command_executor/copilot_cli.py
gpt4_command_executor/executor.py
gpt4_command_executor/gpt3.py
gpt4_command_executor-0.1.dist-info/METADATA
gpt4_command_executor-0.1.dist-info/WHEEL
gpt4_command_executor-0.1.dist-info/entry_points.txt
gpt4_command_executor-0.1.dist-info/top_level.txt
gpt4_command_executor-0.1.dist-info/RECORD
